manosutils/__init__.py
manosutils/myfunctions.py
manosutils-0.1.0.dist-info/METADATA
manosutils-0.1.0.dist-info/WHEEL
manosutils-0.1.0.dist-info/top_level.txt
manosutils-0.1.0.dist-info/RECORD
