Metadata-Version: 2.1
Name: manosutils
Version: 0.1.0
Summary: Things I'm tired of writing manually in a library!
Author: Manos Wagner
License: MIT
